<?xml version="1.0" encoding="utf-8"?>
<font>
    <glyphs>
        <glyph PSName="space" UID="0020">
            <base GID="3"></base>
        </glyph>
        <glyph PSName="exclam" UID="0021">
            <base GID="4"></base>
        </glyph>
        <glyph PSName="quotedbl" UID="0022">
            <base GID="5"></base>
        </glyph>
        <glyph PSName="numbersign" UID="0023">
            <base GID="6"></base>
        </glyph>
        <glyph PSName="dollar" UID="0024">
            <base GID="7"></base>
        </glyph>
        <glyph PSName="percent" UID="0025">
            <base GID="8"></base>
        </glyph>
        <glyph PSName="ampersand" UID="0026">
            <base GID="9"></base>
        </glyph>
        <glyph PSName="quotesingle" UID="0027">
            <base GID="10"></base>
        </glyph>
        <glyph PSName="parenleft" UID="0028">
            <base GID="11"></base>
        </glyph>
        <glyph PSName="parenright" UID="0029">
            <base GID="12"></base>
        </glyph>
        <glyph PSName="asterisk" UID="002A">
            <base GID="13"></base>
        </glyph>
        <glyph PSName="plus" UID="002B">
            <base GID="14"></base>
        </glyph>
        <glyph PSName="comma" UID="002C">
            <base GID="15"></base>
        </glyph>
        <glyph PSName="hyphen" UID="002D">
            <base GID="16"></base>
        </glyph>
        <glyph PSName="period" UID="002E">
            <base GID="17"></base>
        </glyph>
        <glyph PSName="slash" UID="002F">
            <base GID="18"></base>
        </glyph>
        <glyph PSName="zero" UID="0030">
            <base GID="19"></base>
        </glyph>
        <glyph PSName="one" UID="0031">
            <base GID="20"></base>
        </glyph>
        <glyph PSName="two" UID="0032">
            <base GID="21"></base>
        </glyph>
        <glyph PSName="three" UID="0033">
            <base GID="22"></base>
        </glyph>
        <glyph PSName="four" UID="0034">
            <base GID="23"></base>
        </glyph>
        <glyph PSName="five" UID="0035">
            <base GID="24"></base>
        </glyph>
        <glyph PSName="six" UID="0036">
            <base GID="25"></base>
        </glyph>
        <glyph PSName="seven" UID="0037">
            <base GID="26"></base>
        </glyph>
        <glyph PSName="eight" UID="0038">
            <base GID="27"></base>
        </glyph>
        <glyph PSName="nine" UID="0039">
            <base GID="28"></base>
        </glyph>
        <glyph PSName="colon" UID="003A">
            <base GID="29"></base>
        </glyph>
        <glyph PSName="semicolon" UID="003B">
            <base GID="30"></base>
        </glyph>
        <glyph PSName="less" UID="003C">
            <base GID="31"></base>
        </glyph>
        <glyph PSName="equal" UID="003D">
            <base GID="32"></base>
        </glyph>
        <glyph PSName="greater" UID="003E">
            <base GID="33"></base>
        </glyph>
        <glyph PSName="question" UID="003F">
            <base GID="34"></base>
        </glyph>
        <glyph PSName="at" UID="0040">
            <base GID="35"></base>
        </glyph>
        <glyph PSName="A" UID="0041">
            <base GID="36"></base>
        </glyph>
        <glyph PSName="B" UID="0042">
            <base GID="37"></base>
        </glyph>
        <glyph PSName="C" UID="0043">
            <base GID="38"></base>
        </glyph>
        <glyph PSName="D" UID="0044">
            <base GID="39"></base>
        </glyph>
        <glyph PSName="E" UID="0045">
            <base GID="40"></base>
        </glyph>
        <glyph PSName="F" UID="0046">
            <base GID="41"></base>
        </glyph>
        <glyph PSName="G" UID="0047">
            <base GID="42"></base>
        </glyph>
        <glyph PSName="H" UID="0048">
            <base GID="43"></base>
        </glyph>
        <glyph PSName="I" UID="0049">
            <base GID="44"></base>
        </glyph>
        <glyph PSName="J" UID="004A">
            <base GID="45"></base>
        </glyph>
        <glyph PSName="K" UID="004B">
            <base GID="46"></base>
        </glyph>
        <glyph PSName="L" UID="004C">
            <base GID="47"></base>
        </glyph>
        <glyph PSName="M" UID="004D">
            <base GID="48"></base>
        </glyph>
        <glyph PSName="N" UID="004E">
            <base GID="49"></base>
        </glyph>
        <glyph PSName="O" UID="004F">
            <base GID="50"></base>
        </glyph>
        <glyph PSName="P" UID="0050">
            <base GID="51"></base>
        </glyph>
        <glyph PSName="Q" UID="0051">
            <base GID="52"></base>
        </glyph>
        <glyph PSName="R" UID="0052">
            <base GID="53"></base>
        </glyph>
        <glyph PSName="S" UID="0053">
            <base GID="54"></base>
        </glyph>
        <glyph PSName="T" UID="0054">
            <base GID="55"></base>
        </glyph>
        <glyph PSName="U" UID="0055">
            <base GID="56"></base>
        </glyph>
        <glyph PSName="V" UID="0056">
            <base GID="57"></base>
        </glyph>
        <glyph PSName="W" UID="0057">
            <base GID="58"></base>
        </glyph>
        <glyph PSName="X" UID="0058">
            <base GID="59"></base>
        </glyph>
        <glyph PSName="Y" UID="0059">
            <base GID="60"></base>
        </glyph>
        <glyph PSName="Z" UID="005A">
            <base GID="61"></base>
        </glyph>
        <glyph PSName="bracketleft" UID="005B">
            <base GID="62"></base>
        </glyph>
        <glyph PSName="backslash" UID="005C">
            <base GID="63"></base>
        </glyph>
        <glyph PSName="bracketright" UID="005D">
            <base GID="64"></base>
        </glyph>
        <glyph PSName="asciicircum" UID="005E">
            <base GID="65"></base>
        </glyph>
        <glyph PSName="underscore" UID="005F">
            <base GID="66"></base>
        </glyph>
        <glyph PSName="grave" UID="0060">
            <base GID="67"></base>
        </glyph>
        <glyph PSName="a" UID="0061">
            <base GID="68"></base>
        </glyph>
        <glyph PSName="b" UID="0062">
            <base GID="69"></base>
        </glyph>
        <glyph PSName="c" UID="0063">
            <base GID="70"></base>
        </glyph>
        <glyph PSName="d" UID="0064">
            <base GID="71"></base>
        </glyph>
        <glyph PSName="e" UID="0065">
            <base GID="72"></base>
        </glyph>
        <glyph PSName="f" UID="0066">
            <base GID="73"></base>
        </glyph>
        <glyph PSName="g" UID="0067">
            <base GID="74"></base>
        </glyph>
        <glyph PSName="h" UID="0068">
            <base GID="75"></base>
        </glyph>
        <glyph PSName="i" UID="0069">
            <base GID="76"></base>
        </glyph>
        <glyph PSName="j" UID="006A">
            <base GID="77"></base>
        </glyph>
        <glyph PSName="k" UID="006B">
            <base GID="78"></base>
        </glyph>
        <glyph PSName="l" UID="006C">
            <base GID="79"></base>
        </glyph>
        <glyph PSName="m" UID="006D">
            <base GID="80"></base>
        </glyph>
        <glyph PSName="n" UID="006E">
            <base GID="81"></base>
        </glyph>
        <glyph PSName="o" UID="006F">
            <base GID="82"></base>
        </glyph>
        <glyph PSName="p" UID="0070">
            <base GID="83"></base>
        </glyph>
        <glyph PSName="q" UID="0071">
            <base GID="84"></base>
        </glyph>
        <glyph PSName="r" UID="0072">
            <base GID="85"></base>
        </glyph>
        <glyph PSName="s" UID="0073">
            <base GID="86"></base>
        </glyph>
        <glyph PSName="t" UID="0074">
            <base GID="87"></base>
        </glyph>
        <glyph PSName="u" UID="0075">
            <base GID="88"></base>
        </glyph>
        <glyph PSName="v" UID="0076">
            <base GID="89"></base>
        </glyph>
        <glyph PSName="w" UID="0077">
            <base GID="90"></base>
        </glyph>
        <glyph PSName="x" UID="0078">
            <base GID="91"></base>
        </glyph>
        <glyph PSName="y" UID="0079">
            <base GID="92"></base>
        </glyph>
        <glyph PSName="z" UID="007A">
            <base GID="93"></base>
        </glyph>
        <glyph PSName="braceleft" UID="007B">
            <base GID="94"></base>
        </glyph>
        <glyph PSName="bar" UID="007C">
            <base GID="95"></base>
        </glyph>
        <glyph PSName="braceright" UID="007D">
            <base GID="96"></base>
        </glyph>
        <glyph PSName="asciitilde" UID="007E">
            <base GID="97"></base>
        </glyph>
        <glyph PSName="Adieresis" UID="00C4">
            <base GID="98"></base>
        </glyph>
        <glyph PSName="Aring" UID="00C5">
            <base GID="99"></base>
        </glyph>
        <glyph PSName="Ccedilla" UID="00C7">
            <base GID="100"></base>
        </glyph>
        <glyph PSName="Eacute" UID="00C9">
            <base GID="101"></base>
        </glyph>
        <glyph PSName="Ntilde" UID="00D1">
            <base GID="102"></base>
        </glyph>
        <glyph PSName="Odieresis" UID="00D6">
            <base GID="103"></base>
        </glyph>
        <glyph PSName="Udieresis" UID="00DC">
            <base GID="104"></base>
        </glyph>
        <glyph PSName="aacute" UID="00E1">
            <base GID="105"></base>
        </glyph>
        <glyph PSName="agrave" UID="00E0">
            <base GID="106"></base>
        </glyph>
        <glyph PSName="acircumflex" UID="00E2">
            <base GID="107"></base>
        </glyph>
        <glyph PSName="adieresis" UID="00E4">
            <base GID="108"></base>
        </glyph>
        <glyph PSName="atilde" UID="00E3">
            <base GID="109"></base>
        </glyph>
        <glyph PSName="aring" UID="00E5">
            <base GID="110"></base>
        </glyph>
        <glyph PSName="ccedilla" UID="00E7">
            <base GID="111"></base>
        </glyph>
        <glyph PSName="eacute" UID="00E9">
            <base GID="112"></base>
        </glyph>
        <glyph PSName="egrave" UID="00E8">
            <base GID="113"></base>
        </glyph>
        <glyph PSName="ecircumflex" UID="00EA">
            <base GID="114"></base>
        </glyph>
        <glyph PSName="edieresis" UID="00EB">
            <base GID="115"></base>
        </glyph>
        <glyph PSName="iacute" UID="00ED">
            <base GID="116"></base>
        </glyph>
        <glyph PSName="igrave" UID="00EC">
            <base GID="117"></base>
        </glyph>
        <glyph PSName="icircumflex" UID="00EE">
            <base GID="118"></base>
        </glyph>
        <glyph PSName="idieresis" UID="00EF">
            <base GID="119"></base>
        </glyph>
        <glyph PSName="ntilde" UID="00F1">
            <base GID="120"></base>
        </glyph>
        <glyph PSName="oacute" UID="00F3">
            <base GID="121"></base>
        </glyph>
        <glyph PSName="ograve" UID="00F2">
            <base GID="122"></base>
        </glyph>
        <glyph PSName="ocircumflex" UID="00F4">
            <base GID="123"></base>
        </glyph>
        <glyph PSName="odieresis" UID="00F6">
            <base GID="124"></base>
        </glyph>
        <glyph PSName="otilde" UID="00F5">
            <base GID="125"></base>
        </glyph>
        <glyph PSName="uacute" UID="00FA">
            <base GID="126"></base>
        </glyph>
        <glyph PSName="ugrave" UID="00F9">
            <base GID="127"></base>
        </glyph>
        <glyph PSName="ucircumflex" UID="00FB">
            <base GID="128"></base>
        </glyph>
        <glyph PSName="udieresis" UID="00FC">
            <base GID="129"></base>
        </glyph>
        <glyph PSName="dagger" UID="2020">
            <base GID="130"></base>
        </glyph>
        <glyph PSName="degree" UID="00B0">
            <base GID="131"></base>
        </glyph>
        <glyph PSName="cent" UID="00A2">
            <base GID="132"></base>
        </glyph>
        <glyph PSName="sterling" UID="00A3">
            <base GID="133"></base>
        </glyph>
        <glyph PSName="section" UID="00A7">
            <base GID="134"></base>
        </glyph>
        <glyph PSName="bullet" UID="2022">
            <base GID="135"></base>
        </glyph>
        <glyph PSName="paragraph" UID="00B6">
            <base GID="136"></base>
        </glyph>
        <glyph PSName="germandbls" UID="00DF">
            <base GID="137"></base>
        </glyph>
        <glyph PSName="registered" UID="00AE">
            <base GID="138"></base>
        </glyph>
        <glyph PSName="copyright" UID="00A9">
            <base GID="139"></base>
        </glyph>
        <glyph PSName="trademark" UID="2122">
            <base GID="140"></base>
        </glyph>
        <glyph PSName="acute" UID="00B4">
            <base GID="141"></base>
        </glyph>
        <glyph PSName="dieresis" UID="00A8">
            <base GID="142"></base>
        </glyph>
        <glyph PSName="notequal" UID="2260">
            <base GID="143"></base>
        </glyph>
        <glyph PSName="AE" UID="00C6">
            <base GID="144"></base>
        </glyph>
        <glyph PSName="Oslash" UID="00D8">
            <base GID="145"></base>
        </glyph>
        <glyph PSName="infinity" UID="221E">
            <base GID="146"></base>
        </glyph>
        <glyph PSName="plusminus" UID="00B1">
            <base GID="147"></base>
        </glyph>
        <glyph PSName="lessequal" UID="2264">
            <base GID="148"></base>
        </glyph>
        <glyph PSName="greaterequal" UID="2265">
            <base GID="149"></base>
        </glyph>
        <glyph PSName="yen" UID="00A5">
            <base GID="150"></base>
        </glyph>
        <glyph PSName="mu" UID="00B5">
            <base GID="151"></base>
        </glyph>
        <glyph PSName="partialdiff" UID="2202">
            <base GID="152"></base>
        </glyph>
        <glyph PSName="summation" UID="2211">
            <base GID="153"></base>
        </glyph>
        <glyph PSName="product" UID="220F">
            <base GID="154"></base>
        </glyph>
        <glyph PSName="pi" UID="03C0">
            <base GID="155"></base>
        </glyph>
        <glyph PSName="integral" UID="222B">
            <base GID="156"></base>
        </glyph>
        <glyph PSName="ordfeminine" UID="00AA">
            <base GID="157"></base>
        </glyph>
        <glyph PSName="ordmasculine" UID="00BA">
            <base GID="158"></base>
        </glyph>
        <glyph PSName="Omega" UID="2126">
            <base GID="159"></base>
        </glyph>
        <glyph PSName="ae" UID="00E6">
            <base GID="160"></base>
        </glyph>
        <glyph PSName="oslash" UID="00F8">
            <base GID="161"></base>
        </glyph>
        <glyph PSName="questiondown" UID="00BF">
            <base GID="162"></base>
        </glyph>
        <glyph PSName="exclamdown" UID="00A1">
            <base GID="163"></base>
        </glyph>
        <glyph PSName="logicalnot" UID="00AC">
            <base GID="164"></base>
        </glyph>
        <glyph PSName="radical" UID="221A">
            <base GID="165"></base>
        </glyph>
        <glyph PSName="florin" UID="0192">
            <base GID="166"></base>
        </glyph>
        <glyph PSName="approxequal" UID="2248">
            <base GID="167"></base>
        </glyph>
        <glyph PSName="Delta" UID="2206">
            <base GID="168"></base>
        </glyph>
        <glyph PSName="guillemotleft" UID="00AB">
            <base GID="169"></base>
        </glyph>
        <glyph PSName="guillemotright" UID="00BB">
            <base GID="170"></base>
        </glyph>
        <glyph PSName="ellipsis" UID="2026">
            <base GID="171"></base>
        </glyph>
        <glyph PSName="uni00A0" UID="00A0">
            <base GID="172"></base>
        </glyph>
        <glyph PSName="Agrave" UID="00C0">
            <base GID="173"></base>
        </glyph>
        <glyph PSName="Atilde" UID="00C3">
            <base GID="174"></base>
        </glyph>
        <glyph PSName="Otilde" UID="00D5">
            <base GID="175"></base>
        </glyph>
        <glyph PSName="OE" UID="0152">
            <base GID="176"></base>
        </glyph>
        <glyph PSName="oe" UID="0153">
            <base GID="177"></base>
        </glyph>
        <glyph PSName="endash" UID="2013">
            <base GID="178"></base>
        </glyph>
        <glyph PSName="emdash" UID="2014">
            <base GID="179"></base>
        </glyph>
        <glyph PSName="quotedblleft" UID="201C">
            <base GID="180"></base>
        </glyph>
        <glyph PSName="quotedblright" UID="201D">
            <base GID="181"></base>
        </glyph>
        <glyph PSName="quoteleft" UID="2018">
            <base GID="182"></base>
        </glyph>
        <glyph PSName="quoteright" UID="2019">
            <base GID="183"></base>
        </glyph>
        <glyph PSName="divide" UID="00F7">
            <base GID="184"></base>
        </glyph>
        <glyph PSName="lozenge" UID="25CA">
            <base GID="185"></base>
        </glyph>
        <glyph PSName="ydieresis" UID="00FF">
            <base GID="186"></base>
        </glyph>
        <glyph PSName="Ydieresis" UID="0178">
            <base GID="187"></base>
        </glyph>
        <glyph PSName="fraction" UID="2044">
            <base GID="188"></base>
        </glyph>
        <glyph PSName="currency" UID="00A4">
            <base GID="189"></base>
        </glyph>
        <glyph PSName="guilsinglleft" UID="2039">
            <base GID="190"></base>
        </glyph>
        <glyph PSName="guilsinglright" UID="203A">
            <base GID="191"></base>
        </glyph>
        <glyph PSName="fi" UID="FB01">
            <base GID="192"></base>
        </glyph>
        <glyph PSName="fl" UID="FB02">
            <base GID="193"></base>
        </glyph>
        <glyph PSName="daggerdbl" UID="2021">
            <base GID="194"></base>
        </glyph>
        <glyph PSName="periodcentered" UID="00B7">
            <base GID="195"></base>
        </glyph>
        <glyph PSName="quotesinglbase" UID="201A">
            <base GID="196"></base>
        </glyph>
        <glyph PSName="quotedblbase" UID="201E">
            <base GID="197"></base>
        </glyph>
        <glyph PSName="perthousand" UID="2030">
            <base GID="198"></base>
        </glyph>
        <glyph PSName="Acircumflex" UID="00C2">
            <base GID="199"></base>
        </glyph>
        <glyph PSName="Ecircumflex" UID="00CA">
            <base GID="200"></base>
        </glyph>
        <glyph PSName="Aacute" UID="00C1">
            <base GID="201"></base>
        </glyph>
        <glyph PSName="Edieresis" UID="00CB">
            <base GID="202"></base>
        </glyph>
        <glyph PSName="Egrave" UID="00C8">
            <base GID="203"></base>
        </glyph>
        <glyph PSName="Iacute" UID="00CD">
            <base GID="204"></base>
        </glyph>
        <glyph PSName="Icircumflex" UID="00CE">
            <base GID="205"></base>
        </glyph>
        <glyph PSName="Idieresis" UID="00CF">
            <base GID="206"></base>
        </glyph>
        <glyph PSName="Igrave" UID="00CC">
            <base GID="207"></base>
        </glyph>
        <glyph PSName="Oacute" UID="00D3">
            <base GID="208"></base>
        </glyph>
        <glyph PSName="Ocircumflex" UID="00D4">
            <base GID="209"></base>
        </glyph>
        <glyph PSName="uni25CC" UID="25CC">
            <base GID="210"></base>
        </glyph>
        <glyph PSName="Ograve" UID="00D2">
            <base GID="211"></base>
        </glyph>
        <glyph PSName="Uacute" UID="00DA">
            <base GID="212"></base>
        </glyph>
        <glyph PSName="Ucircumflex" UID="00DB">
            <base GID="213"></base>
        </glyph>
        <glyph PSName="Ugrave" UID="00D9">
            <base GID="214"></base>
        </glyph>
        <glyph PSName="dotlessi" UID="0131">
            <base GID="215"></base>
        </glyph>
        <glyph PSName="circumflex" UID="02C6">
            <base GID="216"></base>
        </glyph>
        <glyph PSName="tilde" UID="02DC">
            <base GID="217"></base>
        </glyph>
        <glyph PSName="macron" UID="00AF">
            <base GID="218"></base>
        </glyph>
        <glyph PSName="breve" UID="02D8">
            <base GID="219"></base>
        </glyph>
        <glyph PSName="dotaccent" UID="02D9">
            <base GID="220"></base>
        </glyph>
        <glyph PSName="ring" UID="02DA">
            <base GID="221"></base>
        </glyph>
        <glyph PSName="cedilla" UID="00B8">
            <base GID="222"></base>
        </glyph>
        <glyph PSName="hungarumlaut" UID="02DD">
            <base GID="223"></base>
        </glyph>
        <glyph PSName="ogonek" UID="02DB">
            <base GID="224"></base>
        </glyph>
        <glyph PSName="caron" UID="02C7">
            <base GID="225"></base>
        </glyph>
        <glyph PSName="uni1EAD" UID="1EAD">
            <base GID="226"></base>
        </glyph>
        <glyph PSName="uni1EA5" UID="1EA5">
            <base GID="227"></base>
        </glyph>
        <glyph PSName="uni1EA5.VN">
            <base GID="228"></base>
        </glyph>
        <glyph PSName="uni1EA7" UID="1EA7">
            <base GID="229"></base>
        </glyph>
        <glyph PSName="uni1EA7.VN">
            <base GID="230"></base>
        </glyph>
        <glyph PSName="uni1EAB" UID="1EAB">
            <base GID="231"></base>
        </glyph>
        <glyph PSName="uni1EAB.VN">
            <base GID="232"></base>
        </glyph>
        <glyph PSName="uni1EA9" UID="1EA9">
            <base GID="233"></base>
        </glyph>
        <glyph PSName="uni1EA9.VN">
            <base GID="234"></base>
        </glyph>
        <glyph PSName="abreve" UID="0103">
            <base GID="235"></base>
        </glyph>
        <glyph PSName="uni1EB7" UID="1EB7">
            <base GID="236"></base>
        </glyph>
        <glyph PSName="uni1EAF" UID="1EAF">
            <base GID="237"></base>
        </glyph>
        <glyph PSName="uni1EAF.VN">
            <base GID="238"></base>
        </glyph>
        <glyph PSName="uni1EB1" UID="1EB1">
            <base GID="239"></base>
        </glyph>
        <glyph PSName="uni1EB1.VN">
            <base GID="240"></base>
        </glyph>
        <glyph PSName="uni1EB5" UID="1EB5">
            <base GID="241"></base>
        </glyph>
        <glyph PSName="uni1EB5.VN">
            <base GID="242"></base>
        </glyph>
        <glyph PSName="uni1EB3" UID="1EB3">
            <base GID="243"></base>
        </glyph>
        <glyph PSName="uni1EB3.VN">
            <base GID="244"></base>
        </glyph>
        <glyph PSName="uni01CE" UID="01CE">
            <base GID="245"></base>
        </glyph>
        <glyph PSName="amacron" UID="0101">
            <base GID="246"></base>
        </glyph>
        <glyph PSName="uni01DF" UID="01DF">
            <base GID="247"></base>
        </glyph>
        <glyph PSName="uni0227" UID="0227">
            <base GID="248"></base>
        </glyph>
        <glyph PSName="uni01E1" UID="01E1">
            <base GID="249"></base>
        </glyph>
        <glyph PSName="aringacute" UID="01FB">
            <base GID="250"></base>
        </glyph>
        <glyph PSName="uni1EA3" UID="1EA3">
            <base GID="251"></base>
        </glyph>
        <glyph PSName="uni1EA1" UID="1EA1">
            <base GID="252"></base>
        </glyph>
        <glyph PSName="uni0251" UID="0251">
            <base GID="253"></base>
        </glyph>
        <glyph PSName="a.SngStory">
            <base GID="254"></base>
        </glyph>
        <glyph PSName="aacute.SngStory">
            <base GID="255"></base>
        </glyph>
        <glyph PSName="agrave.SngStory">
            <base GID="256"></base>
        </glyph>
        <glyph PSName="acircumflex.SngStory">
            <base GID="257"></base>
        </glyph>
        <glyph PSName="uni1EAD.SngStory">
            <base GID="258"></base>
        </glyph>
        <glyph PSName="uni1EA5.SngStory">
            <base GID="259"></base>
        </glyph>
        <glyph PSName="uni1EA7.SngStory">
            <base GID="260"></base>
        </glyph>
        <glyph PSName="uni1EAB.SngStory">
            <base GID="261"></base>
        </glyph>
        <glyph PSName="uni1EA9.SngStory">
            <base GID="262"></base>
        </glyph>
        <glyph PSName="abreve.SngStory">
            <base GID="263"></base>
        </glyph>
        <glyph PSName="uni1EB7.SngStory">
            <base GID="264"></base>
        </glyph>
        <glyph PSName="uni1EAF.SngStory">
            <base GID="265"></base>
        </glyph>
        <glyph PSName="uni1EB1.SngStory">
            <base GID="266"></base>
        </glyph>
        <glyph PSName="uni1EB5.SngStory">
            <base GID="267"></base>
        </glyph>
        <glyph PSName="uni1EB3.SngStory">
            <base GID="268"></base>
        </glyph>
        <glyph PSName="uni01CE.SngStory">
            <base GID="269"></base>
        </glyph>
        <glyph PSName="atilde.SngStory">
            <base GID="270"></base>
        </glyph>
        <glyph PSName="amacron.SngStory">
            <base GID="271"></base>
        </glyph>
        <glyph PSName="adieresis.SngStory">
            <base GID="272"></base>
        </glyph>
        <glyph PSName="uni01DF.SngStory">
            <base GID="273"></base>
        </glyph>
        <glyph PSName="uni0227.SngStory">
            <base GID="274"></base>
        </glyph>
        <glyph PSName="uni01E1.SngStory">
            <base GID="275"></base>
        </glyph>
        <glyph PSName="aring.SngStory">
            <base GID="276"></base>
        </glyph>
        <glyph PSName="aringacute.SngStory">
            <base GID="277"></base>
        </glyph>
        <glyph PSName="uni1EA3.SngStory">
            <base GID="278"></base>
        </glyph>
        <glyph PSName="uni1EA1.SngStory">
            <base GID="279"></base>
        </glyph>
        <glyph PSName="aeacute" UID="01FD">
            <base GID="280"></base>
        </glyph>
        <glyph PSName="uni01E3" UID="01E3">
            <base GID="281"></base>
        </glyph>
        <glyph PSName="uni1EA4" UID="1EA4">
            <base GID="282"></base>
        </glyph>
        <glyph PSName="uni1EA4.VN">
            <base GID="283"></base>
        </glyph>
        <glyph PSName="uni1EA6" UID="1EA6">
            <base GID="284"></base>
        </glyph>
        <glyph PSName="uni1EA6.VN">
            <base GID="285"></base>
        </glyph>
        <glyph PSName="uni1EAA" UID="1EAA">
            <base GID="286"></base>
        </glyph>
        <glyph PSName="uni1EAA.VN">
            <base GID="287"></base>
        </glyph>
        <glyph PSName="uni1EA8" UID="1EA8">
            <base GID="288"></base>
        </glyph>
        <glyph PSName="uni1EA8.VN">
            <base GID="289"></base>
        </glyph>
        <glyph PSName="uni1EAC" UID="1EAC">
            <base GID="290"></base>
        </glyph>
        <glyph PSName="Abreve" UID="0102">
            <base GID="291"></base>
        </glyph>
        <glyph PSName="uni1EAE" UID="1EAE">
            <base GID="292"></base>
        </glyph>
        <glyph PSName="uni1EAE.VN">
            <base GID="293"></base>
        </glyph>
        <glyph PSName="uni1EB0" UID="1EB0">
            <base GID="294"></base>
        </glyph>
        <glyph PSName="uni1EB0.VN">
            <base GID="295"></base>
        </glyph>
        <glyph PSName="uni1EB4" UID="1EB4">
            <base GID="296"></base>
        </glyph>
        <glyph PSName="uni1EB4.VN">
            <base GID="297"></base>
        </glyph>
        <glyph PSName="uni1EB2" UID="1EB2">
            <base GID="298"></base>
        </glyph>
        <glyph PSName="uni1EB2.VN">
            <base GID="299"></base>
        </glyph>
        <glyph PSName="uni1EB6" UID="1EB6">
            <base GID="300"></base>
        </glyph>
        <glyph PSName="uni01CD" UID="01CD">
            <base GID="301"></base>
        </glyph>
        <glyph PSName="Amacron" UID="0100">
            <base GID="302"></base>
        </glyph>
        <glyph PSName="uni01DE" UID="01DE">
            <base GID="303"></base>
        </glyph>
        <glyph PSName="uni0226" UID="0226">
            <base GID="304"></base>
        </glyph>
        <glyph PSName="uni01E0" UID="01E0">
            <base GID="305"></base>
        </glyph>
        <glyph PSName="Aringacute" UID="01FA">
            <base GID="306"></base>
        </glyph>
        <glyph PSName="uni1EA2" UID="1EA2">
            <base GID="307"></base>
        </glyph>
        <glyph PSName="uni1EA0" UID="1EA0">
            <base GID="308"></base>
        </glyph>
        <glyph PSName="AEacute" UID="01FC">
            <base GID="309"></base>
        </glyph>
        <glyph PSName="uni01E2" UID="01E2">
            <base GID="310"></base>
        </glyph>
        <glyph PSName="uni1E03" UID="1E03">
            <base GID="311"></base>
        </glyph>
        <glyph PSName="uni1E07" UID="1E07">
            <base GID="312"></base>
        </glyph>
        <glyph PSName="uni1E05" UID="1E05">
            <base GID="313"></base>
        </glyph>
        <glyph PSName="uni0253" UID="0253">
            <base GID="314"></base>
        </glyph>
        <glyph PSName="uni1E02" UID="1E02">
            <base GID="315"></base>
        </glyph>
        <glyph PSName="uni1E06" UID="1E06">
            <base GID="316"></base>
        </glyph>
        <glyph PSName="uni1E04" UID="1E04">
            <base GID="317"></base>
        </glyph>
        <glyph PSName="uni0181" UID="0181">
            <base GID="318"></base>
        </glyph>
        <glyph PSName="cacute" UID="0107">
            <base GID="319"></base>
        </glyph>
        <glyph PSName="ccircumflex" UID="0109">
            <base GID="320"></base>
        </glyph>
        <glyph PSName="ccaron" UID="010D">
            <base GID="321"></base>
        </glyph>
        <glyph PSName="cdotaccent" UID="010B">
            <base GID="322"></base>
        </glyph>
        <glyph PSName="uni1E09" UID="1E09">
            <base GID="323"></base>
        </glyph>
        <glyph PSName="uni0254" UID="0254">
            <base GID="324"></base>
        </glyph>
        <glyph PSName="uni0254.TopSerif">
            <base GID="325"></base>
        </glyph>
        <glyph PSName="Cacute" UID="0106">
            <base GID="326"></base>
        </glyph>
        <glyph PSName="Ccircumflex" UID="0108">
            <base GID="327"></base>
        </glyph>
        <glyph PSName="Ccaron" UID="010C">
            <base GID="328"></base>
        </glyph>
        <glyph PSName="Cdotaccent" UID="010A">
            <base GID="329"></base>
        </glyph>
        <glyph PSName="uni1E08" UID="1E08">
            <base GID="330"></base>
        </glyph>
        <glyph PSName="Euro" UID="20AC">
            <base GID="331"></base>
        </glyph>
        <glyph PSName="uni0186" UID="0186">
            <base GID="332"></base>
        </glyph>
        <glyph PSName="uni0186.TopSerif">
            <base GID="333"></base>
        </glyph>
        <glyph PSName="uni1E0B" UID="1E0B">
            <base GID="334"></base>
        </glyph>
        <glyph PSName="uni1E0F" UID="1E0F">
            <base GID="335"></base>
        </glyph>
        <glyph PSName="uni1E0D" UID="1E0D">
            <base GID="336"></base>
        </glyph>
        <glyph PSName="dcroat" UID="0111">
            <base GID="337"></base>
        </glyph>
        <glyph PSName="uni0257" UID="0257">
            <base GID="338"></base>
        </glyph>
        <glyph PSName="uni0256" UID="0256">
            <base GID="339"></base>
        </glyph>
        <glyph PSName="eth" UID="00F0">
            <base GID="340"></base>
        </glyph>
        <glyph PSName="Dcaron" UID="010E">
            <base GID="341"></base>
        </glyph>
        <glyph PSName="uni1E0A" UID="1E0A">
            <base GID="342"></base>
        </glyph>
        <glyph PSName="uni1E0E" UID="1E0E">
            <base GID="343"></base>
        </glyph>
        <glyph PSName="uni1E0C" UID="1E0C">
            <base GID="344"></base>
        </glyph>
        <glyph PSName="Eth" UID="00D0">
            <base GID="345"></base>
        </glyph>
        <glyph PSName="Dcroat" UID="0110">
            <base GID="346"></base>
        </glyph>
        <glyph PSName="uni0189" UID="0189">
            <base GID="347"></base>
        </glyph>
        <glyph PSName="uni018A" UID="018A">
            <base GID="348"></base>
        </glyph>
        <glyph PSName="uni1EBF" UID="1EBF">
            <base GID="349"></base>
        </glyph>
        <glyph PSName="uni1EBF.VN">
            <base GID="350"></base>
        </glyph>
        <glyph PSName="uni1EC1" UID="1EC1">
            <base GID="351"></base>
        </glyph>
        <glyph PSName="uni1EC1.VN">
            <base GID="352"></base>
        </glyph>
        <glyph PSName="uni1EC5" UID="1EC5">
            <base GID="353"></base>
        </glyph>
        <glyph PSName="uni1EC5.VN">
            <base GID="354"></base>
        </glyph>
        <glyph PSName="uni1EC3" UID="1EC3">
            <base GID="355"></base>
        </glyph>
        <glyph PSName="uni1EC3.VN">
            <base GID="356"></base>
        </glyph>
        <glyph PSName="uni1EC7" UID="1EC7">
            <base GID="357"></base>
        </glyph>
        <glyph PSName="ebreve" UID="0115">
            <base GID="358"></base>
        </glyph>
        <glyph PSName="ecaron" UID="011B">
            <base GID="359"></base>
        </glyph>
        <glyph PSName="uni1EBD" UID="1EBD">
            <base GID="360"></base>
        </glyph>
        <glyph PSName="emacron" UID="0113">
            <base GID="361"></base>
        </glyph>
        <glyph PSName="uni1E17" UID="1E17">
            <base GID="362"></base>
        </glyph>
        <glyph PSName="uni1E15" UID="1E15">
            <base GID="363"></base>
        </glyph>
        <glyph PSName="edotaccent" UID="0117">
            <base GID="364"></base>
        </glyph>
        <glyph PSName="uni1EBB" UID="1EBB">
            <base GID="365"></base>
        </glyph>
        <glyph PSName="uni1EB9" UID="1EB9">
            <base GID="366"></base>
        </glyph>
        <glyph PSName="uni0229" UID="0229">
            <base GID="367"></base>
        </glyph>
        <glyph PSName="uni1E1D" UID="1E1D">
            <base GID="368"></base>
        </glyph>
        <glyph PSName="uni01DD" UID="01DD">
            <base GID="369"></base>
        </glyph>
        <glyph PSName="uni0259" UID="0259">
            <base GID="370"></base>
        </glyph>
        <glyph PSName="uni025B" UID="025B">
            <base GID="371"></base>
        </glyph>
        <glyph PSName="uni1EBE" UID="1EBE">
            <base GID="372"></base>
        </glyph>
        <glyph PSName="uni1EBE.VN">
            <base GID="373"></base>
        </glyph>
        <glyph PSName="uni1EC0" UID="1EC0">
            <base GID="374"></base>
        </glyph>
        <glyph PSName="uni1EC0.VN">
            <base GID="375"></base>
        </glyph>
        <glyph PSName="uni1EC4" UID="1EC4">
            <base GID="376"></base>
        </glyph>
        <glyph PSName="uni1EC4.VN">
            <base GID="377"></base>
        </glyph>
        <glyph PSName="uni1EC2" UID="1EC2">
            <base GID="378"></base>
        </glyph>
        <glyph PSName="uni1EC2.VN">
            <base GID="379"></base>
        </glyph>
        <glyph PSName="uni1EC6" UID="1EC6">
            <base GID="380"></base>
        </glyph>
        <glyph PSName="Ebreve" UID="0114">
            <base GID="381"></base>
        </glyph>
        <glyph PSName="Ecaron" UID="011A">
            <base GID="382"></base>
        </glyph>
        <glyph PSName="uni1EBC" UID="1EBC">
            <base GID="383"></base>
        </glyph>
        <glyph PSName="Emacron" UID="0112">
            <base GID="384"></base>
        </glyph>
        <glyph PSName="uni1E16" UID="1E16">
            <base GID="385"></base>
        </glyph>
        <glyph PSName="uni1E14" UID="1E14">
            <base GID="386"></base>
        </glyph>
        <glyph PSName="Edotaccent" UID="0116">
            <base GID="387"></base>
        </glyph>
        <glyph PSName="uni1EBA" UID="1EBA">
            <base GID="388"></base>
        </glyph>
        <glyph PSName="uni1EB8" UID="1EB8">
            <base GID="389"></base>
        </glyph>
        <glyph PSName="uni0228" UID="0228">
            <base GID="390"></base>
        </glyph>
        <glyph PSName="uni1E1C" UID="1E1C">
            <base GID="391"></base>
        </glyph>
        <glyph PSName="uni018E" UID="018E">
            <base GID="392"></base>
        </glyph>
        <glyph PSName="uni0190" UID="0190">
            <base GID="393"></base>
        </glyph>
        <glyph PSName="uni1E1F" UID="1E1F">
            <base GID="394"></base>
        </glyph>
        <glyph PSName="uni1E1E" UID="1E1E">
            <base GID="395"></base>
        </glyph>
        <glyph PSName="uni01F5" UID="01F5">
            <base GID="396"></base>
        </glyph>
        <glyph PSName="gcircumflex" UID="011D">
            <base GID="397"></base>
        </glyph>
        <glyph PSName="gbreve" UID="011F">
            <base GID="398"></base>
        </glyph>
        <glyph PSName="gcaron" UID="01E7">
            <base GID="399"></base>
        </glyph>
        <glyph PSName="uni1E21" UID="1E21">
            <base GID="400"></base>
        </glyph>
        <glyph PSName="gdotaccent" UID="0121">
            <base GID="401"></base>
        </glyph>
        <glyph PSName="g.SngBowl">
            <base GID="402"></base>
        </glyph>
        <glyph PSName="uni01F5.SngBowl">
            <base GID="403"></base>
        </glyph>
        <glyph PSName="gcircumflex.SngBowl">
            <base GID="404"></base>
        </glyph>
        <glyph PSName="gbreve.SngBowl">
            <base GID="405"></base>
        </glyph>
        <glyph PSName="gcaron.SngBowl">
            <base GID="406"></base>
        </glyph>
        <glyph PSName="uni1E21.SngBowl">
            <base GID="407"></base>
        </glyph>
        <glyph PSName="gdotaccent.SngBowl">
            <base GID="408"></base>
        </glyph>
        <glyph PSName="uni01F4" UID="01F4">
            <base GID="409"></base>
        </glyph>
        <glyph PSName="Gcircumflex" UID="011C">
            <base GID="410"></base>
        </glyph>
        <glyph PSName="Gbreve" UID="011E">
            <base GID="411"></base>
        </glyph>
        <glyph PSName="Gcaron" UID="01E6">
            <base GID="412"></base>
        </glyph>
        <glyph PSName="uni1E20" UID="1E20">
            <base GID="413"></base>
        </glyph>
        <glyph PSName="Gdotaccent" UID="0120">
            <base GID="414"></base>
        </glyph>
        <glyph PSName="hcircumflex" UID="0125">
            <base GID="415"></base>
        </glyph>
        <glyph PSName="uni021F" UID="021F">
            <base GID="416"></base>
        </glyph>
        <glyph PSName="uni1E27" UID="1E27">
            <base GID="417"></base>
        </glyph>
        <glyph PSName="uni1E23" UID="1E23">
            <base GID="418"></base>
        </glyph>
        <glyph PSName="uni1E96" UID="1E96">
            <base GID="419"></base>
        </glyph>
        <glyph PSName="uni1E25" UID="1E25">
            <base GID="420"></base>
        </glyph>
        <glyph PSName="Hcircumflex" UID="0124">
            <base GID="421"></base>
        </glyph>
        <glyph PSName="uni021E" UID="021E">
            <base GID="422"></base>
        </glyph>
        <glyph PSName="uni1E26" UID="1E26">
            <base GID="423"></base>
        </glyph>
        <glyph PSName="uni1E22" UID="1E22">
            <base GID="424"></base>
        </glyph>
        <glyph PSName="uni1E24" UID="1E24">
            <base GID="425"></base>
        </glyph>
        <glyph PSName="Pi" UID="03A0">
            <base GID="426"></base>
        </glyph>
        <glyph PSName="ibreve" UID="012D">
            <base GID="427"></base>
        </glyph>
        <glyph PSName="uni01D0" UID="01D0">
            <base GID="428"></base>
        </glyph>
        <glyph PSName="itilde" UID="0129">
            <base GID="429"></base>
        </glyph>
        <glyph PSName="imacron" UID="012B">
            <base GID="430"></base>
        </glyph>
        <glyph PSName="uni1E2F" UID="1E2F">
            <base GID="431"></base>
        </glyph>
        <glyph PSName="uni1EC9" UID="1EC9">
            <base GID="432"></base>
        </glyph>
        <glyph PSName="uni1ECB" UID="1ECB">
            <base GID="433"></base>
        </glyph>
        <glyph PSName="uni0268" UID="0268">
            <base GID="434"></base>
        </glyph>
        <glyph PSName="i.Dotless">
            <base GID="435"></base>
        </glyph>
        <glyph PSName="uni0268.Dotless">
            <base GID="436"></base>
        </glyph>
        <glyph PSName="ij" UID="0133">
            <base GID="437"></base>
        </glyph>
        <glyph PSName="uni0269" UID="0269">
            <base GID="438"></base>
        </glyph>
        <glyph PSName="Ibreve" UID="012C">
            <base GID="439"></base>
        </glyph>
        <glyph PSName="uni01CF" UID="01CF">
            <base GID="440"></base>
        </glyph>
        <glyph PSName="Itilde" UID="0128">
            <base GID="441"></base>
        </glyph>
        <glyph PSName="Imacron" UID="012A">
            <base GID="442"></base>
        </glyph>
        <glyph PSName="uni1E2E" UID="1E2E">
            <base GID="443"></base>
        </glyph>
        <glyph PSName="Idotaccent" UID="0130">
            <base GID="444"></base>
        </glyph>
        <glyph PSName="uni1EC8" UID="1EC8">
            <base GID="445"></base>
        </glyph>
        <glyph PSName="uni1ECA" UID="1ECA">
            <base GID="446"></base>
        </glyph>
        <glyph PSName="uni0197" UID="0197">
            <base GID="447"></base>
        </glyph>
        <glyph PSName="IJ" UID="0132">
            <base GID="448"></base>
        </glyph>
        <glyph PSName="j.Dotless">
            <base GID="449"></base>
        </glyph>
        <glyph PSName="uni0237" UID="0237">
            <base GID="450"></base>
        </glyph>
        <glyph PSName="uni1E31" UID="1E31">
            <base GID="451"></base>
        </glyph>
        <glyph PSName="uni01E9" UID="01E9">
            <base GID="452"></base>
        </glyph>
        <glyph PSName="uni1E35" UID="1E35">
            <base GID="453"></base>
        </glyph>
        <glyph PSName="uni1E33" UID="1E33">
            <base GID="454"></base>
        </glyph>
        <glyph PSName="uni0199" UID="0199">
            <base GID="455"></base>
        </glyph>
        <glyph PSName="uni1E30" UID="1E30">
            <base GID="456"></base>
        </glyph>
        <glyph PSName="uni01E8" UID="01E8">
            <base GID="457"></base>
        </glyph>
        <glyph PSName="uni1E34" UID="1E34">
            <base GID="458"></base>
        </glyph>
        <glyph PSName="uni1E32" UID="1E32">
            <base GID="459"></base>
        </glyph>
        <glyph PSName="uni0198" UID="0198">
            <base GID="460"></base>
        </glyph>
        <glyph PSName="lacute" UID="013A">
            <base GID="461"></base>
        </glyph>
        <glyph PSName="uni1E3B" UID="1E3B">
            <base GID="462"></base>
        </glyph>
        <glyph PSName="uni1E37" UID="1E37">
            <base GID="463"></base>
        </glyph>
        <glyph PSName="uni1E39" UID="1E39">
            <base GID="464"></base>
        </glyph>
        <glyph PSName="uni019A" UID="019A">
            <base GID="465"></base>
        </glyph>
        <glyph PSName="uni2C61" UID="2C61">
            <base GID="466"></base>
        </glyph>
        <glyph PSName="uni026B" UID="026B">
            <base GID="467"></base>
        </glyph>
        <glyph PSName="lslash" UID="0142">
            <base GID="468"></base>
        </glyph>
        <glyph PSName="Lacute" UID="0139">
            <base GID="469"></base>
        </glyph>
        <glyph PSName="uni1E3A" UID="1E3A">
            <base GID="470"></base>
        </glyph>
        <glyph PSName="uni1E36" UID="1E36">
            <base GID="471"></base>
        </glyph>
        <glyph PSName="uni1E38" UID="1E38">
            <base GID="472"></base>
        </glyph>
        <glyph PSName="uni023D" UID="023D">
            <base GID="473"></base>
        </glyph>
        <glyph PSName="uni2C60" UID="2C60">
            <base GID="474"></base>
        </glyph>
        <glyph PSName="uni2C62" UID="2C62">
            <base GID="475"></base>
        </glyph>
        <glyph PSName="Lslash" UID="0141">
            <base GID="476"></base>
        </glyph>
        <glyph PSName="uni1E3F" UID="1E3F">
            <base GID="477"></base>
        </glyph>
        <glyph PSName="uni1E41" UID="1E41">
            <base GID="478"></base>
        </glyph>
        <glyph PSName="uni1E43" UID="1E43">
            <base GID="479"></base>
        </glyph>
        <glyph PSName="uni1E3E" UID="1E3E">
            <base GID="480"></base>
        </glyph>
        <glyph PSName="uni1E40" UID="1E40">
            <base GID="481"></base>
        </glyph>
        <glyph PSName="uni1E42" UID="1E42">
            <base GID="482"></base>
        </glyph>
        <glyph PSName="nacute" UID="0144">
            <base GID="483"></base>
        </glyph>
        <glyph PSName="uni01F9" UID="01F9">
            <base GID="484"></base>
        </glyph>
        <glyph PSName="ncaron" UID="0148">
            <base GID="485"></base>
        </glyph>
        <glyph PSName="uni1E45" UID="1E45">
            <base GID="486"></base>
        </glyph>
        <glyph PSName="uni1E49" UID="1E49">
            <base GID="487"></base>
        </glyph>
        <glyph PSName="uni1E47" UID="1E47">
            <base GID="488"></base>
        </glyph>
        <glyph PSName="uni0272" UID="0272">
            <base GID="489"></base>
        </glyph>
        <glyph PSName="eng" UID="014B">
            <base GID="490"></base>
        </glyph>
        <glyph PSName="Nacute" UID="0143">
            <base GID="491"></base>
        </glyph>
        <glyph PSName="uni01F8" UID="01F8">
            <base GID="492"></base>
        </glyph>
        <glyph PSName="Ncaron" UID="0147">
            <base GID="493"></base>
        </glyph>
        <glyph PSName="uni1E44" UID="1E44">
            <base GID="494"></base>
        </glyph>
        <glyph PSName="uni1E48" UID="1E48">
            <base GID="495"></base>
        </glyph>
        <glyph PSName="uni1E46" UID="1E46">
            <base GID="496"></base>
        </glyph>
        <glyph PSName="uni019D" UID="019D">
            <base GID="497"></base>
        </glyph>
        <glyph PSName="Eng.UCStyle">
            <base GID="498"></base>
        </glyph>
        <glyph PSName="uni019D.LCStyle">
            <base GID="499"></base>
        </glyph>
        <glyph PSName="Eng.BaselineHook">
            <base GID="500"></base>
        </glyph>
        <glyph PSName="Eng" UID="014A">
            <base GID="501"></base>
        </glyph>
        <glyph PSName="Eng.Kom">
            <base GID="502"></base>
        </glyph>
        <glyph PSName="ohungarumlaut" UID="0151">
            <base GID="503"></base>
        </glyph>
        <glyph PSName="uni1ED1" UID="1ED1">
            <base GID="504"></base>
        </glyph>
        <glyph PSName="uni1ED1.VN">
            <base GID="505"></base>
        </glyph>
        <glyph PSName="uni1ED3" UID="1ED3">
            <base GID="506"></base>
        </glyph>
        <glyph PSName="uni1ED3.VN">
            <base GID="507"></base>
        </glyph>
        <glyph PSName="uni1ED7" UID="1ED7">
            <base GID="508"></base>
        </glyph>
        <glyph PSName="uni1ED7.VN">
            <base GID="509"></base>
        </glyph>
        <glyph PSName="uni1ED5" UID="1ED5">
            <base GID="510"></base>
        </glyph>
        <glyph PSName="uni1ED5.VN">
            <base GID="511"></base>
        </glyph>
        <glyph PSName="uni1ED9" UID="1ED9">
            <base GID="512"></base>
        </glyph>
        <glyph PSName="obreve" UID="014F">
            <base GID="513"></base>
        </glyph>
        <glyph PSName="uni01D2" UID="01D2">
            <base GID="514"></base>
        </glyph>
        <glyph PSName="uni1E4D" UID="1E4D">
            <base GID="515"></base>
        </glyph>
        <glyph PSName="uni022D" UID="022D">
            <base GID="516"></base>
        </glyph>
        <glyph PSName="uni1E4F" UID="1E4F">
            <base GID="517"></base>
        </glyph>
        <glyph PSName="omacron" UID="014D">
            <base GID="518"></base>
        </glyph>
        <glyph PSName="uni1E53" UID="1E53">
            <base GID="519"></base>
        </glyph>
        <glyph PSName="uni1E51" UID="1E51">
            <base GID="520"></base>
        </glyph>
        <glyph PSName="uni022B" UID="022B">
            <base GID="521"></base>
        </glyph>
        <glyph PSName="uni022F" UID="022F">
            <base GID="522"></base>
        </glyph>
        <glyph PSName="uni0231" UID="0231">
            <base GID="523"></base>
        </glyph>
        <glyph PSName="uni1ECF" UID="1ECF">
            <base GID="524"></base>
        </glyph>
        <glyph PSName="uni1ECD" UID="1ECD">
            <base GID="525"></base>
        </glyph>
        <glyph PSName="uni0275" UID="0275">
            <base GID="526"></base>
        </glyph>
        <glyph PSName="oslashacute" UID="01FF">
            <base GID="527"></base>
        </glyph>
        <glyph PSName="emptyset" UID="2205">
            <base GID="528"></base>
        </glyph>
        <glyph PSName="ohorn" UID="01A1">
            <base GID="529"></base>
        </glyph>
        <glyph PSName="uni1EDB" UID="1EDB">
            <base GID="530"></base>
        </glyph>
        <glyph PSName="uni1EDD" UID="1EDD">
            <base GID="531"></base>
        </glyph>
        <glyph PSName="uni1EE1" UID="1EE1">
            <base GID="532"></base>
        </glyph>
        <glyph PSName="uni1EDF" UID="1EDF">
            <base GID="533"></base>
        </glyph>
        <glyph PSName="uni1EE3" UID="1EE3">
            <base GID="534"></base>
        </glyph>
        <glyph PSName="Ohungarumlaut" UID="0150">
            <base GID="535"></base>
        </glyph>
        <glyph PSName="uni1ED0" UID="1ED0">
            <base GID="536"></base>
        </glyph>
        <glyph PSName="uni1ED0.VN">
            <base GID="537"></base>
        </glyph>
        <glyph PSName="uni1ED2" UID="1ED2">
            <base GID="538"></base>
        </glyph>
        <glyph PSName="uni1ED2.VN">
            <base GID="539"></base>
        </glyph>
        <glyph PSName="uni1ED6" UID="1ED6">
            <base GID="540"></base>
        </glyph>
        <glyph PSName="uni1ED6.VN">
            <base GID="541"></base>
        </glyph>
        <glyph PSName="uni1ED4" UID="1ED4">
            <base GID="542"></base>
        </glyph>
        <glyph PSName="uni1ED4.VN">
            <base GID="543"></base>
        </glyph>
        <glyph PSName="uni1ED8" UID="1ED8">
            <base GID="544"></base>
        </glyph>
        <glyph PSName="Obreve" UID="014E">
            <base GID="545"></base>
        </glyph>
        <glyph PSName="uni01D1" UID="01D1">
            <base GID="546"></base>
        </glyph>
        <glyph PSName="uni1E4C" UID="1E4C">
            <base GID="547"></base>
        </glyph>
        <glyph PSName="uni022C" UID="022C">
            <base GID="548"></base>
        </glyph>
        <glyph PSName="uni1E4E" UID="1E4E">
            <base GID="549"></base>
        </glyph>
        <glyph PSName="Omacron" UID="014C">
            <base GID="550"></base>
        </glyph>
        <glyph PSName="uni1E52" UID="1E52">
            <base GID="551"></base>
        </glyph>
        <glyph PSName="uni1E50" UID="1E50">
            <base GID="552"></base>
        </glyph>
        <glyph PSName="uni022A" UID="022A">
            <base GID="553"></base>
        </glyph>
        <glyph PSName="uni022E" UID="022E">
            <base GID="554"></base>
        </glyph>
        <glyph PSName="uni0230" UID="0230">
            <base GID="555"></base>
        </glyph>
        <glyph PSName="uni1ECE" UID="1ECE">
            <base GID="556"></base>
        </glyph>
        <glyph PSName="uni1ECC" UID="1ECC">
            <base GID="557"></base>
        </glyph>
        <glyph PSName="uni019F" UID="019F">
            <base GID="558"></base>
        </glyph>
        <glyph PSName="Oslashacute" UID="01FE">
            <base GID="559"></base>
        </glyph>
        <glyph PSName="Ohorn" UID="01A0">
            <base GID="560"></base>
        </glyph>
        <glyph PSName="uni1EDA" UID="1EDA">
            <base GID="561"></base>
        </glyph>
        <glyph PSName="uni1EDC" UID="1EDC">
            <base GID="562"></base>
        </glyph>
        <glyph PSName="uni1EE0" UID="1EE0">
            <base GID="563"></base>
        </glyph>
        <glyph PSName="uni1EDE" UID="1EDE">
            <base GID="564"></base>
        </glyph>
        <glyph PSName="uni1EE2" UID="1EE2">
            <base GID="565"></base>
        </glyph>
        <glyph PSName="uni03A9" UID="03A9">
            <base GID="566"></base>
        </glyph>
        <glyph PSName="uni1E55" UID="1E55">
            <base GID="567"></base>
        </glyph>
        <glyph PSName="uni1E57" UID="1E57">
            <base GID="568"></base>
        </glyph>
        <glyph PSName="thorn" UID="00FE">
            <base GID="569"></base>
        </glyph>
        <glyph PSName="uni1E54" UID="1E54">
            <base GID="570"></base>
        </glyph>
        <glyph PSName="uni1E56" UID="1E56">
            <base GID="571"></base>
        </glyph>
        <glyph PSName="Thorn" UID="00DE">
            <base GID="572"></base>
        </glyph>
        <glyph PSName="uni02A0" UID="02A0">
            <base GID="573"></base>
        </glyph>
        <glyph PSName="uni024B" UID="024B">
            <base GID="574"></base>
        </glyph>
        <glyph PSName="uni01AA" UID="01AA">
            <base GID="575"></base>
        </glyph>
        <glyph PSName="uni024A" UID="024A">
            <base GID="576"></base>
        </glyph>
        <glyph PSName="racute" UID="0155">
            <base GID="577"></base>
        </glyph>
        <glyph PSName="rcaron" UID="0159">
            <base GID="578"></base>
        </glyph>
        <glyph PSName="uni1E59" UID="1E59">
            <base GID="579"></base>
        </glyph>
        <glyph PSName="uni1E5F" UID="1E5F">
            <base GID="580"></base>
        </glyph>
        <glyph PSName="uni1E5B" UID="1E5B">
            <base GID="581"></base>
        </glyph>
        <glyph PSName="uni1E5D" UID="1E5D">
            <base GID="582"></base>
        </glyph>
        <glyph PSName="Racute" UID="0154">
            <base GID="583"></base>
        </glyph>
        <glyph PSName="Rcaron" UID="0158">
            <base GID="584"></base>
        </glyph>
        <glyph PSName="uni1E58" UID="1E58">
            <base GID="585"></base>
        </glyph>
        <glyph PSName="uni1E5E" UID="1E5E">
            <base GID="586"></base>
        </glyph>
        <glyph PSName="uni1E5A" UID="1E5A">
            <base GID="587"></base>
        </glyph>
        <glyph PSName="uni1E5C" UID="1E5C">
            <base GID="588"></base>
        </glyph>
        <glyph PSName="sacute" UID="015B">
            <base GID="589"></base>
        </glyph>
        <glyph PSName="uni1E65" UID="1E65">
            <base GID="590"></base>
        </glyph>
        <glyph PSName="scircumflex" UID="015D">
            <base GID="591"></base>
        </glyph>
        <glyph PSName="scaron" UID="0161">
            <base GID="592"></base>
        </glyph>
        <glyph PSName="uni1E67" UID="1E67">
            <base GID="593"></base>
        </glyph>
        <glyph PSName="uni1E61" UID="1E61">
            <base GID="594"></base>
        </glyph>
        <glyph PSName="uni1E63" UID="1E63">
            <base GID="595"></base>
        </glyph>
        <glyph PSName="uni1E69" UID="1E69">
            <base GID="596"></base>
        </glyph>
        <glyph PSName="uni0283" UID="0283">
            <base GID="597"></base>
        </glyph>
        <glyph PSName="Sacute" UID="015A">
            <base GID="598"></base>
        </glyph>
        <glyph PSName="uni1E64" UID="1E64">
            <base GID="599"></base>
        </glyph>
        <glyph PSName="Scircumflex" UID="015C">
            <base GID="600"></base>
        </glyph>
        <glyph PSName="Scaron" UID="0160">
            <base GID="601"></base>
        </glyph>
        <glyph PSName="uni1E66" UID="1E66">
            <base GID="602"></base>
        </glyph>
        <glyph PSName="uni1E60" UID="1E60">
            <base GID="603"></base>
        </glyph>
        <glyph PSName="uni1E62" UID="1E62">
            <base GID="604"></base>
        </glyph>
        <glyph PSName="uni1E68" UID="1E68">
            <base GID="605"></base>
        </glyph>
        <glyph PSName="uni1E97" UID="1E97">
            <base GID="606"></base>
        </glyph>
        <glyph PSName="uni1E6B" UID="1E6B">
            <base GID="607"></base>
        </glyph>
        <glyph PSName="uni1E6F" UID="1E6F">
            <base GID="608"></base>
        </glyph>
        <glyph PSName="uni1E6D" UID="1E6D">
            <base GID="609"></base>
        </glyph>
        <glyph PSName="Tcaron" UID="0164">
            <base GID="610"></base>
        </glyph>
        <glyph PSName="uni1E6A" UID="1E6A">
            <base GID="611"></base>
        </glyph>
        <glyph PSName="uni1E6E" UID="1E6E">
            <base GID="612"></base>
        </glyph>
        <glyph PSName="uni1E6C" UID="1E6C">
            <base GID="613"></base>
        </glyph>
        <glyph PSName="uhungarumlaut" UID="0171">
            <base GID="614"></base>
        </glyph>
        <glyph PSName="ubreve" UID="016D">
            <base GID="615"></base>
        </glyph>
        <glyph PSName="uni01D4" UID="01D4">
            <base GID="616"></base>
        </glyph>
        <glyph PSName="utilde" UID="0169">
            <base GID="617"></base>
        </glyph>
        <glyph PSName="uni1E79" UID="1E79">
            <base GID="618"></base>
        </glyph>
        <glyph PSName="umacron" UID="016B">
            <base GID="619"></base>
        </glyph>
        <glyph PSName="uni1E7B" UID="1E7B">
            <base GID="620"></base>
        </glyph>
        <glyph PSName="uni01D8" UID="01D8">
            <base GID="621"></base>
        </glyph>
        <glyph PSName="uni01DC" UID="01DC">
            <base GID="622"></base>
        </glyph>
        <glyph PSName="uni01DA" UID="01DA">
            <base GID="623"></base>
        </glyph>
        <glyph PSName="uni01D6" UID="01D6">
            <base GID="624"></base>
        </glyph>
        <glyph PSName="uring" UID="016F">
            <base GID="625"></base>
        </glyph>
        <glyph PSName="uni1EE7" UID="1EE7">
            <base GID="626"></base>
        </glyph>
        <glyph PSName="uni1EE5" UID="1EE5">
            <base GID="627"></base>
        </glyph>
        <glyph PSName="uni0289" UID="0289">
            <base GID="628"></base>
        </glyph>
        <glyph PSName="uhorn" UID="01B0">
            <base GID="629"></base>
        </glyph>
        <glyph PSName="uni1EE9" UID="1EE9">
            <base GID="630"></base>
        </glyph>
        <glyph PSName="uni1EEB" UID="1EEB">
            <base GID="631"></base>
        </glyph>
        <glyph PSName="uni1EEF" UID="1EEF">
            <base GID="632"></base>
        </glyph>
        <glyph PSName="uni1EED" UID="1EED">
            <base GID="633"></base>
        </glyph>
        <glyph PSName="uni1EF1" UID="1EF1">
            <base GID="634"></base>
        </glyph>
        <glyph PSName="uni028A" UID="028A">
            <base GID="635"></base>
        </glyph>
        <glyph PSName="Uhungarumlaut" UID="0170">
            <base GID="636"></base>
        </glyph>
        <glyph PSName="Ubreve" UID="016C">
            <base GID="637"></base>
        </glyph>
        <glyph PSName="uni01D3" UID="01D3">
            <base GID="638"></base>
        </glyph>
        <glyph PSName="Utilde" UID="0168">
            <base GID="639"></base>
        </glyph>
        <glyph PSName="uni1E78" UID="1E78">
            <base GID="640"></base>
        </glyph>
        <glyph PSName="Umacron" UID="016A">
            <base GID="641"></base>
        </glyph>
        <glyph PSName="uni1E7A" UID="1E7A">
            <base GID="642"></base>
        </glyph>
        <glyph PSName="uni01D7" UID="01D7">
            <base GID="643"></base>
        </glyph>
        <glyph PSName="uni01DB" UID="01DB">
            <base GID="644"></base>
        </glyph>
        <glyph PSName="uni01D9" UID="01D9">
            <base GID="645"></base>
        </glyph>
        <glyph PSName="uni01D5" UID="01D5">
            <base GID="646"></base>
        </glyph>
        <glyph PSName="Uring" UID="016E">
            <base GID="647"></base>
        </glyph>
        <glyph PSName="uni1EE6" UID="1EE6">
            <base GID="648"></base>
        </glyph>
        <glyph PSName="uni1EE4" UID="1EE4">
            <base GID="649"></base>
        </glyph>
        <glyph PSName="uni0244" UID="0244">
            <base GID="650"></base>
        </glyph>
        <glyph PSName="Uhorn" UID="01AF">
            <base GID="651"></base>
        </glyph>
        <glyph PSName="uni1EE8" UID="1EE8">
            <base GID="652"></base>
        </glyph>
        <glyph PSName="uni1EEA" UID="1EEA">
            <base GID="653"></base>
        </glyph>
        <glyph PSName="uni1EEE" UID="1EEE">
            <base GID="654"></base>
        </glyph>
        <glyph PSName="uni1EEC" UID="1EEC">
            <base GID="655"></base>
        </glyph>
        <glyph PSName="uni1EF0" UID="1EF0">
            <base GID="656"></base>
        </glyph>
        <glyph PSName="uni1E7D" UID="1E7D">
            <base GID="657"></base>
        </glyph>
        <glyph PSName="uni1E7F" UID="1E7F">
            <base GID="658"></base>
        </glyph>
        <glyph PSName="uni028C" UID="028C">
            <base GID="659"></base>
        </glyph>
        <glyph PSName="uni0263" UID="0263">
            <base GID="660"></base>
        </glyph>
        <glyph PSName="uni1E7C" UID="1E7C">
            <base GID="661"></base>
        </glyph>
        <glyph PSName="uni1E7E" UID="1E7E">
            <base GID="662"></base>
        </glyph>
        <glyph PSName="uni0245" UID="0245">
            <base GID="663"></base>
        </glyph>
        <glyph PSName="wacute" UID="1E83">
            <base GID="664"></base>
        </glyph>
        <glyph PSName="wgrave" UID="1E81">
            <base GID="665"></base>
        </glyph>
        <glyph PSName="wcircumflex" UID="0175">
            <base GID="666"></base>
        </glyph>
        <glyph PSName="wdieresis" UID="1E85">
            <base GID="667"></base>
        </glyph>
        <glyph PSName="uni1E87" UID="1E87">
            <base GID="668"></base>
        </glyph>
        <glyph PSName="uni1E98" UID="1E98">
            <base GID="669"></base>
        </glyph>
        <glyph PSName="uni1E89" UID="1E89">
            <base GID="670"></base>
        </glyph>
        <glyph PSName="Wacute" UID="1E82">
            <base GID="671"></base>
        </glyph>
        <glyph PSName="Wgrave" UID="1E80">
            <base GID="672"></base>
        </glyph>
        <glyph PSName="Wcircumflex" UID="0174">
            <base GID="673"></base>
        </glyph>
        <glyph PSName="Wdieresis" UID="1E84">
            <base GID="674"></base>
        </glyph>
        <glyph PSName="uni1E86" UID="1E86">
            <base GID="675"></base>
        </glyph>
        <glyph PSName="uni1E88" UID="1E88">
            <base GID="676"></base>
        </glyph>
        <glyph PSName="uni1E8D" UID="1E8D">
            <base GID="677"></base>
        </glyph>
        <glyph PSName="uni1E8B" UID="1E8B">
            <base GID="678"></base>
        </glyph>
        <glyph PSName="uni1E8C" UID="1E8C">
            <base GID="679"></base>
        </glyph>
        <glyph PSName="uni1E8A" UID="1E8A">
            <base GID="680"></base>
        </glyph>
        <glyph PSName="yacute" UID="00FD">
            <base GID="681"></base>
        </glyph>
        <glyph PSName="ygrave" UID="1EF3">
            <base GID="682"></base>
        </glyph>
        <glyph PSName="ycircumflex" UID="0177">
            <base GID="683"></base>
        </glyph>
        <glyph PSName="uni1EF9" UID="1EF9">
            <base GID="684"></base>
        </glyph>
        <glyph PSName="uni0233" UID="0233">
            <base GID="685"></base>
        </glyph>
        <glyph PSName="uni1E8F" UID="1E8F">
            <base GID="686"></base>
        </glyph>
        <glyph PSName="uni1E99" UID="1E99">
            <base GID="687"></base>
        </glyph>
        <glyph PSName="uni1EF7" UID="1EF7">
            <base GID="688"></base>
        </glyph>
        <glyph PSName="uni1EF5" UID="1EF5">
            <base GID="689"></base>
        </glyph>
        <glyph PSName="uni01B4" UID="01B4">
            <base GID="690"></base>
        </glyph>
        <glyph PSName="Yacute" UID="00DD">
            <base GID="691"></base>
        </glyph>
        <glyph PSName="Ygrave" UID="1EF2">
            <base GID="692"></base>
        </glyph>
        <glyph PSName="Ycircumflex" UID="0176">
            <base GID="693"></base>
        </glyph>
        <glyph PSName="uni1EF8" UID="1EF8">
            <base GID="694"></base>
        </glyph>
        <glyph PSName="uni0232" UID="0232">
            <base GID="695"></base>
        </glyph>
        <glyph PSName="uni1E8E" UID="1E8E">
            <base GID="696"></base>
        </glyph>
        <glyph PSName="uni1EF6" UID="1EF6">
            <base GID="697"></base>
        </glyph>
        <glyph PSName="uni1EF4" UID="1EF4">
            <base GID="698"></base>
        </glyph>
        <glyph PSName="uni01B3">
            <base GID="699"></base>
        </glyph>
        <glyph PSName="uni01B3.RtHook" UID="01B3">
            <base GID="700"></base>
        </glyph>
        <glyph PSName="zacute" UID="017A">
            <base GID="701"></base>
        </glyph>
        <glyph PSName="uni1E91" UID="1E91">
            <base GID="702"></base>
        </glyph>
        <glyph PSName="zcaron" UID="017E">
            <base GID="703"></base>
        </glyph>
        <glyph PSName="zdotaccent" UID="017C">
            <base GID="704"></base>
        </glyph>
        <glyph PSName="uni1E95" UID="1E95">
            <base GID="705"></base>
        </glyph>
        <glyph PSName="uni1E93" UID="1E93">
            <base GID="706"></base>
        </glyph>
        <glyph PSName="Zacute" UID="0179">
            <base GID="707"></base>
        </glyph>
        <glyph PSName="uni1E90" UID="1E90">
            <base GID="708"></base>
        </glyph>
        <glyph PSName="Zcaron" UID="017D">
            <base GID="709"></base>
        </glyph>
        <glyph PSName="Zdotaccent" UID="017B">
            <base GID="710"></base>
        </glyph>
        <glyph PSName="uni1E94" UID="1E94">
            <base GID="711"></base>
        </glyph>
        <glyph PSName="uni1E92" UID="1E92">
            <base GID="712"></base>
        </glyph>
        <glyph PSName="uni01A9" UID="01A9">
            <base GID="713"></base>
        </glyph>
        <glyph PSName="uni0292" UID="0292">
            <base GID="714"></base>
        </glyph>
        <glyph PSName="uni01EF" UID="01EF">
            <base GID="715"></base>
        </glyph>
        <glyph PSName="uni01B7" UID="01B7">
            <base GID="716"></base>
        </glyph>
        <glyph PSName="uni01EE" UID="01EE">
            <base GID="717"></base>
        </glyph>
        <glyph PSName="uni0294" UID="0294">
            <base GID="718"></base>
        </glyph>
        <glyph PSName="uni02C0" UID="02C0">
            <base GID="719"></base>
        </glyph>
        <glyph PSName="uni0242" UID="0242">
            <base GID="720"></base>
        </glyph>
        <glyph PSName="uni0241" UID="0241">
            <base GID="721"></base>
        </glyph>
        <glyph PSName="onesuperior" UID="00B9">
            <base GID="722"></base>
        </glyph>
        <glyph PSName="twosuperior" UID="00B2">
            <base GID="723"></base>
        </glyph>
        <glyph PSName="threesuperior" UID="00B3">
            <base GID="724"></base>
        </glyph>
        <glyph PSName="onehalf" UID="00BD">
            <base GID="725"></base>
        </glyph>
        <glyph PSName="onequarter" UID="00BC">
            <base GID="726"></base>
        </glyph>
        <glyph PSName="threequarters" UID="00BE">
            <base GID="727"></base>
        </glyph>
        <glyph PSName="uniA78B" UID="A78B">
            <base GID="728"></base>
        </glyph>
        <glyph PSName="uniA78B.Lrg">
            <base GID="729"></base>
        </glyph>
        <glyph PSName="uniA78C" UID="A78C">
            <base GID="730"></base>
        </glyph>
        <glyph PSName="uniA78C.Lrg">
            <base GID="731"></base>
        </glyph>
        <glyph PSName="uniA789" UID="A789">
            <base GID="732"></base>
        </glyph>
        <glyph PSName="uniA789.Wide">
            <base GID="733"></base>
        </glyph>
        <glyph PSName="uni02BC" UID="02BC">
            <base GID="734"></base>
        </glyph>
        <glyph PSName="uni02BC.Lrg">
            <base GID="735"></base>
        </glyph>
        <glyph PSName="uni2219" UID="2219">
            <base GID="736"></base>
        </glyph>
        <glyph PSName="brokenbar" UID="00A6">
            <base GID="737"></base>
        </glyph>
        <glyph PSName="uni2011" UID="2011">
            <base GID="738"></base>
        </glyph>
        <glyph PSName="uni00AD" UID="00AD">
            <base GID="739"></base>
        </glyph>
        <glyph PSName="minus" UID="2212">
            <base GID="740"></base>
        </glyph>
        <glyph PSName="uni02D7" UID="02D7">
            <base GID="741"></base>
        </glyph>
        <glyph PSName="uni02CA" UID="02CA">
            <base GID="742"></base>
        </glyph>
        <glyph PSName="acutecomb" UID="0301">
            <base GID="743"></base>
        </glyph>
        <glyph PSName="uni030B" UID="030B">
            <base GID="744"></base>
        </glyph>
        <glyph PSName="uni02CB" UID="02CB">
            <base GID="745"></base>
        </glyph>
        <glyph PSName="gravecomb" UID="0300">
            <base GID="746"></base>
        </glyph>
        <glyph PSName="uni0302" UID="0302">
            <base GID="747"></base>
        </glyph>
        <glyph PSName="uni0302_acutecomb.VN">
            <base GID="748"></base>
        </glyph>
        <glyph PSName="uni0302_gravecomb.VN">
            <base GID="749"></base>
        </glyph>
        <glyph PSName="uni0302_tildecomb.VN">
            <base GID="750"></base>
        </glyph>
        <glyph PSName="uni0302_hookabovecomb.VN">
            <base GID="751"></base>
        </glyph>
        <glyph PSName="uni0306" UID="0306">
            <base GID="752"></base>
        </glyph>
        <glyph PSName="uni0306_acutecomb.VN">
            <base GID="753"></base>
        </glyph>
        <glyph PSName="uni0306_gravecomb.VN">
            <base GID="754"></base>
        </glyph>
        <glyph PSName="uni0306_tildecomb.VN">
            <base GID="755"></base>
        </glyph>
        <glyph PSName="uni0306_hookabovecomb.VN">
            <base GID="756"></base>
        </glyph>
        <glyph PSName="uni030C" UID="030C">
            <base GID="757"></base>
        </glyph>
        <glyph PSName="tildecomb" UID="0303">
            <base GID="758"></base>
        </glyph>
        <glyph PSName="multiply" UID="00D7">
            <base GID="759"></base>
        </glyph>
        <glyph PSName="uni02CD" UID="02CD">
            <base GID="760"></base>
        </glyph>
        <glyph PSName="uni0331" UID="0331">
            <base GID="761"></base>
        </glyph>
        <glyph PSName="uni02C9" UID="02C9">
            <base GID="762"></base>
        </glyph>
        <glyph PSName="uni0304" UID="0304">
            <base GID="763"></base>
        </glyph>
        <glyph PSName="uni0304.Short">
            <base GID="764"></base>
        </glyph>
        <glyph PSName="uni035F" UID="035F">
            <base GID="765"></base>
        </glyph>
        <glyph PSName="uni035E" UID="035E">
            <base GID="766"></base>
        </glyph>
        <glyph PSName="uni033F" UID="033F">
            <base GID="767"></base>
        </glyph>
        <glyph PSName="uniA78A" UID="A78A">
            <base GID="768"></base>
        </glyph>
        <glyph PSName="uni0308" UID="0308">
            <base GID="769"></base>
        </glyph>
        <glyph PSName="dotbelowcomb" UID="0323">
            <base GID="770"></base>
        </glyph>
        <glyph PSName="uni0307" UID="0307">
            <base GID="771"></base>
        </glyph>
        <glyph PSName="uni031B" UID="031B">
            <base GID="772"></base>
        </glyph>
        <glyph PSName="uni030A" UID="030A">
            <base GID="773"></base>
        </glyph>
        <glyph PSName="hookabovecomb" UID="0309">
            <base GID="774"></base>
        </glyph>
        <glyph PSName="uni0327" UID="0327">
            <base GID="775"></base>
        </glyph>
        <glyph PSName="uni0328" UID="0328">
            <base GID="776"></base>
        </glyph>
        <glyph PSName="uniF130" UID="F130">
            <base GID="794"></base>
        </glyph>
        <glyph PSName="uniF131" UID="F131">
            <base GID="795"></base>
        </glyph>
        <glyph PSName="acutecomb.LP">
            <base GID="777"></base>
        </glyph>
        <glyph PSName="gravecomb.LP">
            <base GID="778"></base>
        </glyph>
        <glyph PSName="uni0302.LP">
            <base GID="779"></base>
        </glyph>
        <glyph PSName="uni0302_acutecomb.VNLP">
            <base GID="780"></base>
        </glyph>
        <glyph PSName="uni0302_gravecomb.VNLP">
            <base GID="781"></base>
        </glyph>
        <glyph PSName="uni0302_tildecomb.VNLP">
            <base GID="782"></base>
        </glyph>
        <glyph PSName="uni0302_hookabovecomb.VNLP">
            <base GID="783"></base>
        </glyph>
        <glyph PSName="uni0306_acutecomb.VNLP">
            <base GID="784"></base>
        </glyph>
        <glyph PSName="uni0306_gravecomb.VNLP">
            <base GID="785"></base>
        </glyph>
        <glyph PSName="uni0306_tildecomb.VNLP">
            <base GID="786"></base>
        </glyph>
        <glyph PSName="uni0306_hookabovecomb.VNLP">
            <base GID="787"></base>
        </glyph>
        <glyph PSName="uni030C.LP">
            <base GID="788"></base>
        </glyph>
        <glyph PSName="tildecomb.LP">
            <base GID="789"></base>
        </glyph>
        <glyph PSName="uni0304.LP">
            <base GID="790"></base>
        </glyph>
        <glyph PSName="uni0308.LP">
            <base GID="791"></base>
        </glyph>
        <glyph PSName="uni0307.LP">
            <base GID="792"></base>
        </glyph>
        <glyph PSName=".notAccess">
            <base GID="793"></base>
        </glyph>
    </glyphs>
</font>
